utility/__init__.py
utility/config.py
utility/db.py
utility/exception_handler.py
utility/json_handler.py
utility/logger_handler.py
utility/mongo_handler.py
utility/path_handler.py
utility/request_handler.py
utility/time_handler.py
utility_liron_revah-0.0.14.dist-info/LICENSE
utility_liron_revah-0.0.14.dist-info/METADATA
utility_liron_revah-0.0.14.dist-info/WHEEL
utility_liron_revah-0.0.14.dist-info/top_level.txt
utility_liron_revah-0.0.14.dist-info/RECORD
