Metadata-Version: 2.1
Name: utility-liron-revah
Version: 0.0.14
Summary: A small utility package for my own projects
Home-page: https://github.com/liron7722/Utility
Author: Liron Revah
Author-email: revahliron@gmail.com
License: UNKNOWN
Project-URL: Bug Tracker, https://github.com/liron7722/Utility/issues
Platform: UNKNOWN
Classifier: Programming Language :: Python :: 3
Classifier: License :: OSI Approved :: MIT License
Classifier: Operating System :: OS Independent
Requires-Python: >=3.6
License-File: LICENSE
Requires-Dist: CMRESHandler
Requires-Dist: numpy
Requires-Dist: pymongo
Requires-Dist: requests
Requires-Dist: dnspython
